galtab/__init__.py
galtab/_galaxy_tabulator.py
galtab/_version.py
galtab/galtab.py
galtab/moments.py
galtab/jaxhalotools/__init__.py
galtab/jaxhalotools/empirical_models.py
galtab/obs/__init__.py
galtab/obs/obs.py
galtab/obs/test_obs.py
galtab/paper2/README.md
galtab/paper2/__init__.py
galtab/paper2/accuracy_vs_runtime.py
galtab/paper2/clean_desi_data.py
galtab/paper2/count_desi_randoms.py
galtab/paper2/desi_observables.py
galtab/paper2/desi_sv3_pointings.py
galtab/paper2/importance.py
galtab/paper2/kuan_mcmc_script.py
galtab/paper2/mpi_test_script.py
galtab/paper2/param_config.py
galtab/paper2/param_sampler.py
galtab/paper2/tabulation_systematics_forecast.py
galtab/paper2/plots/PaperPlots.ipynb
galtab/tests/test_galtab.py
galtab-1.1.0.dist-info/LICENSE.rst
galtab-1.1.0.dist-info/METADATA
galtab-1.1.0.dist-info/WHEEL
galtab-1.1.0.dist-info/top_level.txt
galtab-1.1.0.dist-info/RECORD
