Metadata-Version: 2.1
Name: galtab
Version: 1.1.0
Summary: Galaxy tabulation: HOD counts-in-cells statistics with JAX
Author-email: Alan Pearl <alanpearl13@gmail.com>
License: MIT License
Project-URL: home, https://github.com/AlanPearl/galtab
Classifier: Programming Language :: Python :: 3
Requires-Python: >=3.9
License-File: LICENSE.rst
Requires-Dist: numpy
Requires-Dist: scipy
Requires-Dist: jax
Requires-Dist: halotools>=0.8.2
Requires-Dist: h5py
Requires-Dist: pandas
Requires-Dist: astropy
Requires-Dist: tqdm
Requires-Dist: fast3tree
Requires-Dist: pathlib
Requires-Dist: Pyarrow
